deepctl_core/__init__.py
deepctl_core/auth.py
deepctl_core/base_command.py
deepctl_core/base_group_command.py
deepctl_core/client.py
deepctl_core/config.py
deepctl_core/models.py
deepctl_core/output.py
deepctl_core/plugin_manager.py
deepctl_core/py.typed
deepctl_core/timing.py
deepctl_core-0.1.10.dist-info/METADATA
deepctl_core-0.1.10.dist-info/WHEEL
deepctl_core-0.1.10.dist-info/top_level.txt
deepctl_core-0.1.10.dist-info/RECORD
